fdat/__init__.py
fdat/__main__.py
fdat/data.py
fdat/diff.py
fdat/intensityratio.py
fdat/log.py
fdat/materials.py
fdat-0.1.0.dist-info/LICENSE
fdat-0.1.0.dist-info/METADATA
fdat-0.1.0.dist-info/WHEEL
fdat-0.1.0.dist-info/entry_points.txt
fdat-0.1.0.dist-info/top_level.txt
fdat-0.1.0.dist-info/RECORD
