Metadata-Version: 2.1
Name: fdat
Version: 0.1.0
Summary: Fast Diffraction Analysis Tool
Home-page: https://github.com/amundmr/fdat
Author: Amund Raniseth
Author-email: amund.raniseth@gmail.com
License: GNU General Public License v3.0
Download-URL: https://github.com/amundmr/fdat/archive/refs/tags/v0.1.0.tar.gz
Keywords: diffraction,plotter,reader,analysis,x-rays,x-ray pattern
Platform: UNKNOWN
Classifier: Development Status :: 3 - Alpha
Classifier: Intended Audience :: Developers
Classifier: Topic :: Software Development :: Build Tools
Classifier: License :: OSI Approved :: GNU General Public License v3 (GPLv3)
Classifier: Programming Language :: Python :: 3
Classifier: Programming Language :: Python :: 3.4
Classifier: Programming Language :: Python :: 3.5
Classifier: Programming Language :: Python :: 3.6
Classifier: Programming Language :: Python :: 3.7
Classifier: Programming Language :: Python :: 3.8
Classifier: Programming Language :: Python :: 3.9
License-File: LICENSE
Requires-Dist: matplotlib
Requires-Dist: numpy
Requires-Dist: pandas
Requires-Dist: toml
Requires-Dist: scipy
Requires-Dist: PyCifRW
Requires-Dist: ecdh
